argparse/__init__.py
argparse/argparse_translation.py
gxargparse/__init__.py
gxargparse/check_path.py
gxargparse-0.2.5.dist-info/top_level.txt
gxargparse-0.2.5.dist-info/entry_points.txt
gxargparse-0.2.5.dist-info/METADATA
gxargparse-0.2.5.dist-info/DESCRIPTION.rst
gxargparse-0.2.5.dist-info/metadata.json
gxargparse-0.2.5.dist-info/WHEEL
gxargparse-0.2.5.dist-info/RECORD
