Metadata-Version: 2.0
Name: gxargparse
Version: 0.2.5
Summary: Galaxy drop-in replacement for argparse
Home-page: https://github.com/erasche/gxargparse
Author: Eric Rasche
Author-email: rasche.eric@yandex.ru
License: UNKNOWN
Platform: UNKNOWN
Classifier: Development Status :: 3 - Alpha
Classifier: Operating System :: OS Independent
Classifier: Intended Audience :: Developers
Classifier: Environment :: Console
Classifier: License :: OSI Approved :: Apache Software License
Requires-Dist: galaxyxml
